dlm397_package/__init__.py
dlm397_package/test.py
dlm397_package/essentials/__init__.py
dlm397_package/essentials/config_loader.py
dlm397_package/essentials/data_save.py
dlm397_package/essentials/example.py
dlm397_package/plotting/__init__.py
dlm397_package-1.0.0.dist-info/METADATA
dlm397_package-1.0.0.dist-info/WHEEL
dlm397_package-1.0.0.dist-info/licenses/LICENSE
dlm397_package-1.0.0.dist-info/RECORD
