Metadata-Version: 2.4
Name: dlm397_package
Version: 1.0.0
Summary: A package I use for processing data.
Project-URL: Homepage, https://github.com/dlm397/Plasma_lib
Project-URL: Issues, https://github.com/dlm397/Plasma_lib
Author-email: dlm397 <dlm397@drexel.edu>
License-Expression: MIT
License-File: LICENSE
Classifier: Operating System :: OS Independent
Classifier: Programming Language :: Python :: 3
Requires-Python: >=3.9
